{
  "$schema": "http://json-schema.org/draft-07/schema#",
  "type": "object",
  "definitions": {
    "DeploymentProfile": {
      "patternProperties": {
        "^[A-Za-z_][A-Za-z0-9_]*$": {
          "additionalProperties": false,
          "properties": {
            "Modes": {
              "description": "A nested object with the deployment mode name as the root and childs based on component types",
              "type": "object"
            }
          }
        }
      },
      "type": "object"
    }
  },
  "$id": "https://docs.hamlet.io/schema/latest/blueprint/schema-reference-deploymentprofile-schema.json"
}
